DicomRTTool/ReaderWriter.py
DicomRTTool/Viewer.py
DicomRTTool/__init__.py
DicomRTTool/key_list.txt
DicomRTTool/template_RS.dcm
DicomRTTool/Services/DicomBases.py
DicomRTTool/Services/StaticScripts.py
DicomRTTool/Services/__init__.py
DicomRTTool-2.2.0.dist-info/LICENSE.txt
DicomRTTool-2.2.0.dist-info/METADATA
DicomRTTool-2.2.0.dist-info/WHEEL
DicomRTTool-2.2.0.dist-info/top_level.txt
DicomRTTool-2.2.0.dist-info/RECORD
