Metadata-Version: 2.1
Name: DicomRTTool
Version: 2.2.0
Summary: Services for reading dicom files, RT structures, and dose files, as well as tools for converting numpy prediction masks back to an RT structure
Home-page: https://github.com/brianmanderson/Dicom_RT_and_Images_to_Mask
Author: Brian Mark Anderson
Author-email: b5anderson@health.ucsd.edu
Classifier: Programming Language :: Python :: 3
Classifier: License :: OSI Approved :: GNU Affero General Public License v3
License-File: LICENSE.txt
Requires-Dist: numpy
Requires-Dist: matplotlib
Requires-Dist: opencv-python
Requires-Dist: openpyxl
Requires-Dist: pandas
Requires-Dist: Pillow
Requires-Dist: pydicom
Requires-Dist: scikit-image
Requires-Dist: scipy
Requires-Dist: SimpleITK
Requires-Dist: six
Requires-Dist: xlrd
Requires-Dist: check-manifest
Requires-Dist: tqdm
Requires-Dist: pytest
Requires-Dist: NiftiResampler
Requires-Dist: PlotScrollNumpyArrays
